{
    "users": [
        {
            "id": 25088037,
            "firstName": "Eliane",
            "lastName": "Ratke",
            "email": "Ocie_Dooley83@gmail.com"
        },
        {
            "id": 60163518,
            "firstName": "Marcos",
            "lastName": "Sawayn",
            "email": "Eda76@yahoo.com"
        },
        {
            "id": 32629603,
            "firstName": "Alford",
            "lastName": "Donnelly",
            "email": "Jaylan59@hotmail.com"
        },
        {
            "id": 90772502,
            "firstName": "Terry",
            "lastName": "Corkery",
            "email": "Darrick.Larkin81@hotmail.com"
        }
    ]
}